[
  {
    "title": "Khăn ướt baby thiên phúc gói 100 tờ - giá sỉ hà nội",
    "price": 1000,
    "original_price": 18000,
    "discount_pct": 94,
    "quantity": 15,
    "time_slot": "17:00",
    "image_url": "https://down-bs-vn.img.susercontent.com/vn-11134207-820l4-mid9x5xwcxe07e_tn",
    "product_link": "https://s.shopee.vn/an_redir?origin_link=https%3A%2F%2Fshopee.vn%2Fopaanlp%2F440183421%2F7893404629&affiliate_id=17351620126&sub_id=1k172606"
  },
  {
    "title": "[Hàng Loại 1] Giá Đỡ Điện Thoại livestream xem video Ổn Định Xoay 360 Độ dùng để Quay Phim Ghi Hình Đa Dụng",
    "price": 9000,
    "original_price": 50000,
    "discount_pct": 82,
    "quantity": 25,
    "time_slot": "17:00",
    "image_url": "https://down-bs-vn.img.susercontent.com/ac6b493c9dbac63c47ded0732c045956_tn",
    "product_link": "https://s.shopee.vn/an_redir?origin_link=https%3A%2F%2Fshopee.vn%2Fopaanlp%2F210876591%2F4157832854&affiliate_id=17351620126&sub_id=9k172606"
  },
  {
    "title": "01 Móc Treo Đồ Inox K5 Dành Cho Mọi Xe Máy Inox 201 - VT103",
    "price": 9000,
    "original_price": 50000,
    "discount_pct": 82,
    "quantity": 24,
    "time_slot": "17:00",
    "image_url": "https://down-bs-vn.img.susercontent.com/vn-11134207-7ra0g-m9k384f3sigy04_tn",
    "product_link": "https://s.shopee.vn/an_redir?origin_link=https%3A%2F%2Fshopee.vn%2Fopaanlp%2F98773981%2F2314368288&affiliate_id=17351620126&sub_id=9k172606"
  },
  {
    "title": "Thìa muỗng inox 304 DandiHome cao cấp, sang trọng (1 chiếc)",
    "price": 9000,
    "original_price": 39500,
    "discount_pct": 77,
    "quantity": 20,
    "time_slot": "17:00",
    "image_url": "https://down-bs-vn.img.susercontent.com/vn-11134207-7ra0g-m7bnmq2jm0uwb0_tn",
    "product_link": "https://s.shopee.vn/an_redir?origin_link=https%3A%2F%2Fshopee.vn%2Fopaanlp%2F62602178%2F4835489713&affiliate_id=17351620126&sub_id=9k172606"
  },
  {
    "title": "Aurora Glow Dot Star Blush Pháp Mắt Mèo Móng Tay Giả Dễ Thương Có Thể Tháo Rời Móng Tay Nhân Tạo Cho Bé Gái Nữ Thời Trang",
    "price": 9000,
    "original_price": 42000,
    "discount_pct": 79,
    "quantity": 10,
    "time_slot": "17:00",
    "image_url": "https://down-bs-vn.img.susercontent.com/sg-11134201-82625-mmgz9eqqmbyae1_tn",
    "product_link": "https://s.shopee.vn/an_redir?origin_link=https%3A%2F%2Fshopee.vn%2Fopaanlp%2F1695918869%2F43929643195&affiliate_id=17351620126&sub_id=9k172606"
  },
  {
    "title": "Cây lăn bụi quần áo JYoohome làm sạch quần áo giường chiếu chăn màn lông thú cưng lõi lăn thay thế",
    "price": 9000,
    "original_price": 30000,
    "discount_pct": 70,
    "quantity": 25,
    "time_slot": "17:00",
    "image_url": "https://down-bs-vn.img.susercontent.com/vn-11134207-7qukw-lilhwz86b4ekef_tn",
    "product_link": "https://s.shopee.vn/an_redir?origin_link=https%3A%2F%2Fshopee.vn%2Fopaanlp%2F895809787%2F21370245253&affiliate_id=17351620126&sub_id=9k172606"
  },
  {
    "title": "{ Combo 2 } Tất Nam Nữ Màu Trẻ Trung Năng Động Chất Liệu cotton TOL-234",
    "price": 9000,
    "original_price": 39000,
    "discount_pct": 77,
    "quantity": 210,
    "time_slot": "17:00",
    "image_url": "https://down-bs-vn.img.susercontent.com/sg-11134201-823p8-mpd6uefb06izbd_tn",
    "product_link": "https://s.shopee.vn/an_redir?origin_link=https%3A%2F%2Fshopee.vn%2Fopaanlp%2F228342708%2F50612077678&affiliate_id=17351620126&sub_id=9k172606"
  },
  {
    "title": "Thắt Lưng Vô Hình Nam Nữ Phong Cách Hàn Quốc, THắt Lưng Co Giãn Đàn Hồi Có Thể Điều Chỉnh,  KOKO TL301",
    "price": 9000,
    "original_price": 30000,
    "discount_pct": 70,
    "quantity": 35,
    "time_slot": "17:00",
    "image_url": "https://down-bs-vn.img.susercontent.com/sg-11134201-7rdwm-md176d30jcva35_tn",
    "product_link": "https://s.shopee.vn/an_redir?origin_link=https%3A%2F%2Fshopee.vn%2Fopaanlp%2F839944157%2F41361543638&affiliate_id=17351620126&sub_id=9k172606"
  },
  {
    "title": "Áo ống croptop kiểu nữ đen trắng trơn bozip ôm body thun gân co giãn xinh VANISA CT035",
    "price": 9000,
    "original_price": 30000,
    "discount_pct": 70,
    "quantity": 35,
    "time_slot": "17:00",
    "image_url": "https://down-bs-vn.img.susercontent.com/f838362a4c7c11041131ef9f907062ce_tn",
    "product_link": "https://s.shopee.vn/an_redir?origin_link=https%3A%2F%2Fshopee.vn%2Fopaanlp%2F745159271%2F16861918860&affiliate_id=17351620126&sub_id=9k172606"
  },
  {
    "title": "Hộp 10 Cây Bút Chì Gỗ Mocha Socola 2B HB Deli Nusign Thân Gỗ Đen Cao Cấp, Viết Êm, Dễ Gọt Phù Hợp Học Sinh & Văn Phòng",
    "price": 9000,
    "original_price": 20000,
    "discount_pct": 55,
    "quantity": 100,
    "time_slot": "17:00",
    "image_url": "https://down-bs-vn.img.susercontent.com/vn-11134207-81ztc-mo9lb4v0tqm869_tn",
    "product_link": "https://s.shopee.vn/an_redir?origin_link=https%3A%2F%2Fshopee.vn%2Fopaanlp%2F1021396369%2F43031159102&affiliate_id=17351620126&sub_id=9k172606"
  },
  {
    "title": "Bát Nhựa Amori - Inochi: Sang Trọng, An Toàn, Tiện Dụng Cho Mọi Bữa Ăn 🍽️✨",
    "price": 9000,
    "original_price": 22000,
    "discount_pct": 59,
    "quantity": 10,
    "time_slot": "17:00",
    "image_url": "https://down-bs-vn.img.susercontent.com/vn-11134207-81ztc-mprn0a1kcv0g48_tn",
    "product_link": "https://s.shopee.vn/an_redir?origin_link=https%3A%2F%2Fshopee.vn%2Fopaanlp%2F634792583%2F15556771935&affiliate_id=17351620126&sub_id=9k172606"
  },
  {
    "title": "Thùng 30 gói khăn giấy ăn cao cấp LUALA 4 lớp, giấy ăn rút mềm mại siêu dai không chất tẩy trắng an toàn sức khoẻ",
    "price": 9000,
    "original_price": 50000,
    "discount_pct": 82,
    "quantity": 25,
    "time_slot": "17:00",
    "image_url": "https://down-bs-vn.img.susercontent.com/vn-11134207-81ztc-moz82bzzogen34_tn",
    "product_link": "https://s.shopee.vn/an_redir?origin_link=https%3A%2F%2Fshopee.vn%2Fopaanlp%2F1638331358%2F45056990117&affiliate_id=17351620126&sub_id=9k172606"
  },
  {
    "title": "[HCM] Tăm bông cho bé sơ sinh V-Coool, hộp que mềm mịn",
    "price": 9000,
    "original_price": 30000,
    "discount_pct": 70,
    "quantity": 25,
    "time_slot": "17:00",
    "image_url": "https://down-bs-vn.img.susercontent.com/vn-11134207-7ras8-m4stndl5xjug20_tn",
    "product_link": "https://s.shopee.vn/an_redir?origin_link=https%3A%2F%2Fshopee.vn%2Fopaanlp%2F255435129%2F23250250278&affiliate_id=17351620126&sub_id=9k172606"
  },
  {
    "title": "Túi màng bọc thực phẩm JYoohome chất liệu PE co dãn có chun siêu dai, Túi gấu bọc đồ ăn",
    "price": 9000,
    "original_price": 15000,
    "discount_pct": 34,
    "quantity": 100,
    "time_slot": "17:00",
    "image_url": "https://down-bs-vn.img.susercontent.com/vn-11134207-7r98o-lusqvfd3s8pxca_tn",
    "product_link": "https://s.shopee.vn/an_redir?origin_link=https%3A%2F%2Fshopee.vn%2Fopaanlp%2F365181681%2F21151340707&affiliate_id=17351620126&sub_id=9k172606"
  },
  {
    "title": "Kẹp ngọc trai phong cách Hàn Quốc lớn Kẹp tóc nữ Khối lượng nhiều hơn Kẹp tóc cá mập",
    "price": 16128,
    "original_price": 22400,
    "discount_pct": 28,
    "quantity": 55,
    "time_slot": "17:00",
    "image_url": "https://down-bs-vn.img.susercontent.com/sg-11134201-7rdwm-lzhkpd5qn0s78f_tn",
    "product_link": "https://s.shopee.vn/an_redir?origin_link=https%3A%2F%2Fshopee.vn%2Fopaanlp%2F331883788%2F24385356114&affiliate_id=17351620126&sub_id=ot172606"
  },
  {
    "title": "Bột giặt Lix Extra hương chanh 550gr EC055 thơm mát làm sạch mọi vết bẩn cứng đầu cho giặt tay và máy",
    "price": 25116,
    "original_price": 29900,
    "discount_pct": 16,
    "quantity": 10,
    "time_slot": "17:00",
    "image_url": "https://down-bs-vn.img.susercontent.com/vn-11134207-7ras8-mcug91ydowq50e_tn",
    "product_link": "https://s.shopee.vn/an_redir?origin_link=https%3A%2F%2Fshopee.vn%2Fopaanlp%2F779607831%2F19005436966&affiliate_id=17351620126&sub_id=ot172606"
  },
  {
    "title": "Bông mút trang điểm IMAGIC sử dụng khô/ ướt trang điểm hoàn hảo 8g",
    "price": 25758,
    "original_price": 34344,
    "discount_pct": 25,
    "quantity": 1800,
    "time_slot": "17:00",
    "image_url": "https://down-bs-vn.img.susercontent.com/cn-11134207-7ras8-m8fqyogbxhct40_tn",
    "product_link": "https://s.shopee.vn/an_redir?origin_link=https%3A%2F%2Fshopee.vn%2Fopaanlp%2F170368383%2F6275976256&affiliate_id=17351620126&sub_id=ot172606"
  },
  {
    "title": "Kính Cường Lực ZAGG GLASS, Bảo Vệ Mạnh Mẽ, Hạn Chế Va Đập, Trầy Xước dành cho iPhone X/XS/11Pro/13/14/15/16",
    "price": 29000,
    "original_price": 70000,
    "discount_pct": 59,
    "quantity": 10,
    "time_slot": "17:00",
    "image_url": "https://down-bs-vn.img.susercontent.com/vn-11134207-81ztc-mny44oe4mhvod6_tn",
    "product_link": "https://s.shopee.vn/an_redir?origin_link=https%3A%2F%2Fshopee.vn%2Fopaanlp%2F164018338%2F28455516866&affiliate_id=17351620126&sub_id=ot172606"
  },
  {
    "title": "Sách: 7 Thói Quen Thách Thức Tiềm Năng Sáng Tạo",
    "price": 29000,
    "original_price": 70000,
    "discount_pct": 59,
    "quantity": 10,
    "time_slot": "17:00",
    "image_url": "https://down-bs-vn.img.susercontent.com/sg-11134201-23010-9xpfqszyeamvaf_tn",
    "product_link": "https://s.shopee.vn/an_redir?origin_link=https%3A%2F%2Fshopee.vn%2Fopaanlp%2F478263048%2F23618603816&affiliate_id=17351620126&sub_id=ot172606"
  },
  {
    "title": "Sữa non bột Laccatter 100gr bổ sung dinh dưỡng cho chó mèo từ 1 tháng tuổi",
    "price": 29000,
    "original_price": 60000,
    "discount_pct": 52,
    "quantity": 10,
    "time_slot": "17:00",
    "image_url": "https://down-bs-vn.img.susercontent.com/vn-11134207-81ztc-mnla0tbnxath87_tn",
    "product_link": "https://s.shopee.vn/an_redir?origin_link=https%3A%2F%2Fshopee.vn%2Fopaanlp%2F299481339%2F26163612151&affiliate_id=17351620126&sub_id=ot172606"
  },
  {
    "title": "Kính cường lực chống nhìn trộm dành cho iPhone 16 Promax 6/7/8 Plus X/Xs/Xr 11 12 13 14 15 Plus Pro Max - TT CASE",
    "price": 29000,
    "original_price": 60000,
    "discount_pct": 52,
    "quantity": 5,
    "time_slot": "17:00",
    "image_url": "https://down-bs-vn.img.susercontent.com/sg-11134201-820oh-mnuxi18nuosl68_tn",
    "product_link": "https://s.shopee.vn/an_redir?origin_link=https%3A%2F%2Fshopee.vn%2Fopaanlp%2F1520328585%2F49059967187&affiliate_id=17351620126&sub_id=ot172606"
  },
  {
    "title": "Phích cắm điện thông minh Kenno, đầu nối siêu gọn 1 ra 3 Q3 chịu tải 2500W màu trắng",
    "price": 29000,
    "original_price": 66700,
    "discount_pct": 57,
    "quantity": 24,
    "time_slot": "17:00",
    "image_url": "https://down-bs-vn.img.susercontent.com/vn-11134207-7r98o-lvb7nq3d0qz1f5_tn",
    "product_link": "https://s.shopee.vn/an_redir?origin_link=https%3A%2F%2Fshopee.vn%2Fopaanlp%2F66333094%2F1737929000&affiliate_id=17351620126&sub_id=ot172606"
  },
  {
    "title": "[HÀNG LOẠI 1] Phụ kiện Gấu treo túi, làm móc chìa khoá nhỏ xinh - chắc chắn cute dễ thương",
    "price": 29000,
    "original_price": 50000,
    "discount_pct": 42,
    "quantity": 50,
    "time_slot": "17:00",
    "image_url": "https://down-bs-vn.img.susercontent.com/vn-11134207-820l4-mfh5a8wm9czs00_tn",
    "product_link": "https://s.shopee.vn/an_redir?origin_link=https%3A%2F%2Fshopee.vn%2Fopaanlp%2F126897108%2F14162033198&affiliate_id=17351620126&sub_id=ot172606"
  },
  {
    "title": "Combo 40 Móc Dán Tường Siêu Dính, Móc Inox 304 Chắc Chắn, Treo Đồ Nhà Tắm, Nhà Bếp Tiện Lợi",
    "price": 29000,
    "original_price": 69000,
    "discount_pct": 58,
    "quantity": 25,
    "time_slot": "17:00",
    "image_url": "https://down-bs-vn.img.susercontent.com/vn-11134207-81ztc-mnxpqwjhdkw4df_tn",
    "product_link": "https://s.shopee.vn/an_redir?origin_link=https%3A%2F%2Fshopee.vn%2Fopaanlp%2F958306443%2F57860076533&affiliate_id=17351620126&sub_id=ot172606"
  },
  {
    "title": "Mũ Bảo Hiểm 1/2 Nửa Đầu Sơn Đủ Màu Kiểu Dáng N088 Loại Rẻ Thuộc Top Bán Chạy",
    "price": 29000,
    "original_price": 89000,
    "discount_pct": 67,
    "quantity": 20,
    "time_slot": "17:00",
    "image_url": "https://down-bs-vn.img.susercontent.com/vn-11134207-7r98o-lni3rpwzwkj11e_tn",
    "product_link": "https://s.shopee.vn/an_redir?origin_link=https%3A%2F%2Fshopee.vn%2Fopaanlp%2F26715862%2F23985145206&affiliate_id=17351620126&sub_id=ot172606"
  },
  {
    "title": "Dây chuyền nữ Eleanor Accessories đa dạng kiểu dáng phụ kiện trang sức vòng cổ thời trang 3893",
    "price": 29000,
    "original_price": 185000,
    "discount_pct": 84,
    "quantity": 25,
    "time_slot": "17:00",
    "image_url": "https://down-bs-vn.img.susercontent.com/vn-11134207-7r98o-lrwvdx2fnue14a_tn",
    "product_link": "https://s.shopee.vn/an_redir?origin_link=https%3A%2F%2Fshopee.vn%2Fopaanlp%2F297412293%2F18102327133&affiliate_id=17351620126&sub_id=ot172606"
  },
  {
    "title": "Túi giấy mặt kính đựng hoa quà tặng túi quà, phụ kiện hoa [Size 15x25x35]",
    "price": 29000,
    "original_price": 61000,
    "discount_pct": 52,
    "quantity": 10,
    "time_slot": "17:00",
    "image_url": "https://down-bs-vn.img.susercontent.com/vn-11134207-7r98o-lwv2969w6b4rde_tn",
    "product_link": "https://s.shopee.vn/an_redir?origin_link=https%3A%2F%2Fshopee.vn%2Fopaanlp%2F265094677%2F28903545008&affiliate_id=17351620126&sub_id=ot172606"
  },
  {
    "title": "30 Miếng dán móng tay phát sáng cho trẻ em, miếng dán móng tay hoạt hình bé gái an toàn phát sáng không thấm nước",
    "price": 29000,
    "original_price": 55000,
    "discount_pct": 47,
    "quantity": 35,
    "time_slot": "17:00",
    "image_url": "https://down-bs-vn.img.susercontent.com/sg-11134201-81ztx-miixxsjikdmr16_tn",
    "product_link": "https://s.shopee.vn/an_redir?origin_link=https%3A%2F%2Fshopee.vn%2Fopaanlp%2F367890943%2F40727393549&affiliate_id=17351620126&sub_id=ot172606"
  },
  {
    "title": "HM97034 Cây Lau Bàn Bếp Tự Vắt Thông Minh Mini 25cm, Bọt Biển Siêu Thấm Hút Đa Năng",
    "price": 29000,
    "original_price": 50000,
    "discount_pct": 42,
    "quantity": 10,
    "time_slot": "17:00",
    "image_url": "https://down-bs-vn.img.susercontent.com/vn-11134207-7ras8-mctgemvd2yccfc_tn",
    "product_link": "https://s.shopee.vn/an_redir?origin_link=https%3A%2F%2Fshopee.vn%2Fopaanlp%2F832892001%2F41560929142&affiliate_id=17351620126&sub_id=ot172606"
  },
  {
    "title": "COMBO 100 Miếng Giấy Lau Sàn Hoà Tan Khử Khuẩn Cao, Làm Sạch Đa Năng Mọi Loại Bụi Bẩn, Dầu Mỡ Tiện Lợi  MH",
    "price": 29000,
    "original_price": 65000,
    "discount_pct": 55,
    "quantity": 30,
    "time_slot": "17:00",
    "image_url": "https://down-bs-vn.img.susercontent.com/sg-11134201-8225z-mhjz6bcwpa8503_tn",
    "product_link": "https://s.shopee.vn/an_redir?origin_link=https%3A%2F%2Fshopee.vn%2Fopaanlp%2F1265379714%2F50202192995&affiliate_id=17351620126&sub_id=ot172606"
  },
  {
    "title": "[Choice] Mũ lưỡi trai nam nữ Jussy Official thêu chữ Her form mềm thời trang Hàn Quốc",
    "price": 29000,
    "original_price": 90000,
    "discount_pct": 68,
    "quantity": 25,
    "time_slot": "17:00",
    "image_url": "https://down-bs-vn.img.susercontent.com/vn-11134207-7ras8-m177mcyus8zf5a_tn",
    "product_link": "https://s.shopee.vn/an_redir?origin_link=https%3A%2F%2Fshopee.vn%2Fopaanlp%2F22431875%2F29913722217&affiliate_id=17351620126&sub_id=ot172606"
  },
  {
    "title": "Kính Áp tròng MCK1 UYAAI Lens Mắt Màu Đen Cận Mắt Quỷ Đen lens Mắt Màu Nâu lens giãn tròng to 14.5mm",
    "price": 29000,
    "original_price": 58000,
    "discount_pct": 50,
    "quantity": 140,
    "time_slot": "17:00",
    "image_url": "https://down-bs-vn.img.susercontent.com/sg-11134201-8260y-ml4dha030c1t3c_tn",
    "product_link": "https://s.shopee.vn/an_redir?origin_link=https%3A%2F%2Fshopee.vn%2Fopaanlp%2F486997610%2F24932816606&affiliate_id=17351620126&sub_id=ot172606"
  },
  {
    "title": "Chai Chiết Dầu Gội Sữa Tắm Trong Suốt, Hộp Đựng Nước Rửa Tay, Nước Rửa Bát Đa Năng, Chai Đựng Dầu Gội, Lọ Đựng Sữa Tắm",
    "price": 29000,
    "original_price": 58000,
    "discount_pct": 50,
    "quantity": 580,
    "time_slot": "17:00",
    "image_url": "https://down-bs-vn.img.susercontent.com/vn-11134207-7r98o-lz2tx2g13vdt43_tn",
    "product_link": "https://s.shopee.vn/an_redir?origin_link=https%3A%2F%2Fshopee.vn%2Fopaanlp%2F123094057%2F19466257088&affiliate_id=17351620126&sub_id=ot172606"
  },
  {
    "title": "Bông tẩy trang Silcot Nhật Bản Hộp 82 miếng cao cấp - Bông Silcot Unicharm",
    "price": 34800,
    "original_price": 60000,
    "discount_pct": 42,
    "quantity": 100,
    "time_slot": "17:00",
    "image_url": "https://down-bs-vn.img.susercontent.com/vn-11134207-81ztc-mmb7ql333caq0f_tn",
    "product_link": "https://s.shopee.vn/an_redir?origin_link=https%3A%2F%2Fshopee.vn%2Fopaanlp%2F89266543%2F25469569646&affiliate_id=17351620126&sub_id=ot172606"
  },
  {
    "title": "[Chính Hãng 201m] Bông tẩy trang LMLer 201 miếng cotton tự nhiên mềm mịn P0642",
    "price": 41800,
    "original_price": 55000,
    "discount_pct": 24,
    "quantity": 700,
    "time_slot": "17:00",
    "image_url": "https://down-bs-vn.img.susercontent.com/vn-11134211-820l4-mgmasif4nj0p43_tn",
    "product_link": "https://s.shopee.vn/an_redir?origin_link=https%3A%2F%2Fshopee.vn%2Fopaanlp%2F175889782%2F25155082237&affiliate_id=17351620126&sub_id=ot172606"
  },
  {
    "title": "Bánh Dừa Nướng Mè Ngọc Thuận, Đạt Chuẩn OCOP | Ít Đường | Hộp 400g",
    "price": 49140,
    "original_price": 63000,
    "discount_pct": 22,
    "quantity": 30,
    "time_slot": "17:00",
    "image_url": "https://down-bs-vn.img.susercontent.com/vn-11134207-820l4-mjo8rm7e2875e1_tn",
    "product_link": "https://s.shopee.vn/an_redir?origin_link=https%3A%2F%2Fshopee.vn%2Fopaanlp%2F1591683032%2F28639418428&affiliate_id=17351620126&sub_id=ot172606"
  },
  {
    "title": "1KG Đậu Gà Mỹ (size 9mm) Thiên Thảo Organic",
    "price": 56050,
    "original_price": 95000,
    "discount_pct": 41,
    "quantity": 50,
    "time_slot": "17:00",
    "image_url": "https://down-bs-vn.img.susercontent.com/sg-11134201-824hc-mpu58c71bh1c4d_tn",
    "product_link": "https://s.shopee.vn/an_redir?origin_link=https%3A%2F%2Fshopee.vn%2Fopaanlp%2F183949248%2F20081954442&affiliate_id=17351620126&sub_id=ot172606"
  },
  {
    "title": "Bột Rang Muối Hộp 350G - Thương Hiệu Bu Phương Ẩm Thực - Không Chất Bảo Quản",
    "price": 64000,
    "original_price": 80000,
    "discount_pct": 20,
    "quantity": 25,
    "time_slot": "17:00",
    "image_url": "https://down-bs-vn.img.susercontent.com/vn-11134207-81ztc-moatmz4l6dqnda_tn",
    "product_link": "https://s.shopee.vn/an_redir?origin_link=https%3A%2F%2Fshopee.vn%2Fopaanlp%2F1209488033%2F25944005757&affiliate_id=17351620126&sub_id=ot172606"
  },
  {
    "title": "Bột Bánh Xèo Hộp 500G - Thương Hiệu Bu Phương Ẩm Thực, Bột Làm Bánh Xèo Chuẩn Vị Truyền Thống",
    "price": 64800,
    "original_price": 90000,
    "discount_pct": 28,
    "quantity": 50,
    "time_slot": "17:00",
    "image_url": "https://down-bs-vn.img.susercontent.com/vn-11134207-81ztc-moau4l8pyw3za6_tn",
    "product_link": "https://s.shopee.vn/an_redir?origin_link=https%3A%2F%2Fshopee.vn%2Fopaanlp%2F1209488033%2F43507199466&affiliate_id=17351620126&sub_id=ot172606"
  },
  {
    "title": "Gối định hình đầu cho bé chống bẹp đầu làm gối chặn cho trẻ sơ sinh chất xô muslin Vipkid chống méo đầu gối cao su non",
    "price": 118300,
    "original_price": 169000,
    "discount_pct": 30,
    "quantity": 105,
    "time_slot": "17:00",
    "image_url": "https://down-bs-vn.img.susercontent.com/vn-11134207-7r98o-lpoyih4yg57806_tn",
    "product_link": "https://s.shopee.vn/an_redir?origin_link=https%3A%2F%2Fshopee.vn%2Fopaanlp%2F20390895%2F24104939717&affiliate_id=17351620126&sub_id=ot172606"
  },
  {
    "title": "Gia Vị Nộm Gà Xe Phay - Thương Hiệu Bu Phương Ẩm Thực (Chuyên Làm Nộm Gà, Nộm Tai Heo, Nộm Chay)",
    "price": 126000,
    "original_price": 150000,
    "discount_pct": 16,
    "quantity": 50,
    "time_slot": "17:00",
    "image_url": "https://down-bs-vn.img.susercontent.com/vn-11134207-81ztc-moewpbvqtafifc_tn",
    "product_link": "https://s.shopee.vn/an_redir?origin_link=https%3A%2F%2Fshopee.vn%2Fopaanlp%2F1209488033%2F50253546745&affiliate_id=17351620126&sub_id=ot172606"
  },
  {
    "title": "Combo 20 chân gà rút xương tê cay - ĂN CÙNG BÀ TUYẾT M28",
    "price": 198000,
    "original_price": 300000,
    "discount_pct": 34,
    "quantity": 50,
    "time_slot": "17:00",
    "image_url": "https://down-bs-vn.img.susercontent.com/vn-11134207-81ztc-mo57bqj5k54y41_tn",
    "product_link": "https://s.shopee.vn/an_redir?origin_link=https%3A%2F%2Fshopee.vn%2Fopaanlp%2F279658061%2F43508358436&affiliate_id=17351620126&sub_id=ot172606"
  },
  {
    "title": "Combo 2 túi nước giặt Lix Matic hương nước hoa  3.2kg giặt tẩy mọi vết bẩn cứng đầu dùng cho máy giặt cửa trước",
    "price": 238000,
    "original_price": 350000,
    "discount_pct": 32,
    "quantity": 15,
    "time_slot": "17:00",
    "image_url": "https://down-bs-vn.img.susercontent.com/vn-11134207-7ras8-md13sx1wecgs47_tn",
    "product_link": "https://s.shopee.vn/an_redir?origin_link=https%3A%2F%2Fshopee.vn%2Fopaanlp%2F779607831%2F24564178381&affiliate_id=17351620126&sub_id=ot172606"
  },
  {
    "title": "Dụng cụ gỡ lưỡi câu và buộc lưỡi câu tiện lợi đi câu fishing",
    "price": 1000,
    "original_price": 17500,
    "discount_pct": 94,
    "quantity": 20,
    "time_slot": "19:00",
    "image_url": "https://down-bs-vn.img.susercontent.com/vn-11134207-81ztc-mlvczzqtv4zpaa_tn",
    "product_link": "https://s.shopee.vn/an_redir?origin_link=https%3A%2F%2Fshopee.vn%2Fopaanlp%2F177903337%2F26594311079&affiliate_id=17351620126&sub_id=1k192606"
  },
  {
    "title": "Chân cắm phao câu đài 2 lớp chống sốc tiện lợi",
    "price": 1000,
    "original_price": 18500,
    "discount_pct": 95,
    "quantity": 20,
    "time_slot": "19:00",
    "image_url": "https://down-bs-vn.img.susercontent.com/vn-11134207-81ztc-mmai85v1xzpe98_tn",
    "product_link": "https://s.shopee.vn/an_redir?origin_link=https%3A%2F%2Fshopee.vn%2Fopaanlp%2F177903337%2F26006552246&affiliate_id=17351620126&sub_id=1k192606"
  },
  {
    "title": "Giá Đỡ Điện Thoại, Giá Đỡ Máy Tính Bảng S059 Dùng Xem Phim, Xem Video",
    "price": 9000,
    "original_price": 35000,
    "discount_pct": 74,
    "quantity": 25,
    "time_slot": "19:00",
    "image_url": "https://down-bs-vn.img.susercontent.com/vn-11134207-7ras8-mchn65zee0d81d_tn",
    "product_link": "https://s.shopee.vn/an_redir?origin_link=https%3A%2F%2Fshopee.vn%2Fopaanlp%2F7661171%2F9518458527&affiliate_id=17351620126&sub_id=9k192606"
  },
  {
    "title": "Tất thờitrang  dạng viên nén nhỏ gọn tiện lợi, bề mặt Lưới co giản thoáng khí",
    "price": 9000,
    "original_price": 20000,
    "discount_pct": 55,
    "quantity": 20,
    "time_slot": "19:00",
    "image_url": "https://down-bs-vn.img.susercontent.com/vn-11134207-7r98o-lvzabn9bzba152_tn",
    "product_link": "https://s.shopee.vn/an_redir?origin_link=https%3A%2F%2Fshopee.vn%2Fopaanlp%2F689783153%2F28551508593&affiliate_id=17351620126&sub_id=9k192606"
  },
  {
    "title": "Phim hoạt hình dễ thương Nơ màu hồng HelloKitty Vỏ khung ngôi sao đầy màu sắc cho IPhone 11 15 16 13 14 12 Pro Max 7 8 Plus X XS Max XR 15 16 14 6 6S Plus SE 2020 Vỏ bột lấp lánh sang trọng",
    "price": 9000,
    "original_price": 37000,
    "discount_pct": 76,
    "quantity": 20,
    "time_slot": "19:00",
    "image_url": "https://down-bs-vn.img.susercontent.com/sg-11134201-8258c-mftlnl83dxxp21_tn",
    "product_link": "https://s.shopee.vn/an_redir?origin_link=https%3A%2F%2Fshopee.vn%2Fopaanlp%2F78560932%2F44424099404&affiliate_id=17351620126&sub_id=9k192606"
  },
  {
    "title": "Miếng Dán Điện Thoại / Cáp Sạc Mophie 30W USB-C to USB-C",
    "price": 9000,
    "original_price": 60000,
    "discount_pct": 85,
    "quantity": 8,
    "time_slot": "19:00",
    "image_url": "https://down-bs-vn.img.susercontent.com/vn-11134207-81ztc-mp15tcmqnaq462_tn",
    "product_link": "https://s.shopee.vn/an_redir?origin_link=https%3A%2F%2Fshopee.vn%2Fopaanlp%2F1003510740%2F57261617003&affiliate_id=17351620126&sub_id=9k192606"
  },
  {
    "title": "Combo 5 cục Cao Su Chùi Keo Dụng Cụ Làm Đồ Da - Da Thuộc Sài Gòn",
    "price": 9000,
    "original_price": 31000,
    "discount_pct": 71,
    "quantity": 25,
    "time_slot": "19:00",
    "image_url": "https://down-bs-vn.img.susercontent.com/sg-11134201-7rdw5-m1l4kvjyvmm59b_tn",
    "product_link": "https://s.shopee.vn/an_redir?origin_link=https%3A%2F%2Fshopee.vn%2Fopaanlp%2F89838526%2F7122313144&affiliate_id=17351620126&sub_id=9k192606"
  },
  {
    "title": "TẶNG Miếng Lót mũ bảo hiểm XÁM",
    "price": 9000,
    "original_price": 30000,
    "discount_pct": 70,
    "quantity": 26,
    "time_slot": "19:00",
    "image_url": "https://down-bs-vn.img.susercontent.com/vn-11134207-81ztc-ml943yez785kf6_tn",
    "product_link": "https://s.shopee.vn/an_redir?origin_link=https%3A%2F%2Fshopee.vn%2Fopaanlp%2F1325972710%2F41772983506&affiliate_id=17351620126&sub_id=9k192606"
  },
  {
    "title": "Kính cường lực điện thoại dành cho iphone trong suốt chống vân tay, chống trầy, cảm ứng mượt",
    "price": 9000,
    "original_price": 50000,
    "discount_pct": 82,
    "quantity": 30,
    "time_slot": "19:00",
    "image_url": "https://down-bs-vn.img.susercontent.com/vn-11134207-81ztc-movc3phethjid4_tn",
    "product_link": "https://s.shopee.vn/an_redir?origin_link=https%3A%2F%2Fshopee.vn%2Fopaanlp%2F65417237%2F48511419101&affiliate_id=17351620126&sub_id=9k192606"
  },
  {
    "title": "COMBO 2 Viên Pin Ma-xell AA",
    "price": 9000,
    "original_price": 40000,
    "discount_pct": 78,
    "quantity": 40,
    "time_slot": "19:00",
    "image_url": "https://down-bs-vn.img.susercontent.com/vn-11134207-81ztc-mn3rw7f6ik1u4c_tn",
    "product_link": "https://s.shopee.vn/an_redir?origin_link=https%3A%2F%2Fshopee.vn%2Fopaanlp%2F178614538%2F40577249469&affiliate_id=17351620126&sub_id=9k192606"
  },
  {
    "title": "Kính Cường Lực Iphone Basefast full HD độ cứng 9H dán màn hình iPhone 8 X Xs Max 11 12 13 14 Pro max",
    "price": 9000,
    "original_price": 30000,
    "discount_pct": 70,
    "quantity": 71,
    "time_slot": "19:00",
    "image_url": "https://down-bs-vn.img.susercontent.com/vn-11134201-7r98o-lw8o7y78hq12e3_tn",
    "product_link": "https://s.shopee.vn/an_redir?origin_link=https%3A%2F%2Fshopee.vn%2Fopaanlp%2F1051609213%2F26002245130&affiliate_id=17351620126&sub_id=9k192606"
  },
  {
    "title": "Dây sạc nhanh USB to LN Basefast 2.4A cho Phone 7 8P xr xs max 11 12 13 pro Cáp bọc dù dài chống gãy",
    "price": 9000,
    "original_price": 39000,
    "discount_pct": 77,
    "quantity": 20,
    "time_slot": "19:00",
    "image_url": "https://down-bs-vn.img.susercontent.com/vn-11134207-820l4-mdyczznuoiyr35_tn",
    "product_link": "https://s.shopee.vn/an_redir?origin_link=https%3A%2F%2Fshopee.vn%2Fopaanlp%2F1051609213%2F26156512798&affiliate_id=17351620126&sub_id=9k192606"
  },
  {
    "title": "Tất vớ lưới mùa hè Jengiang chất liệu ren thoáng khí, thoải mái, thấm hút mồ hôi phong cách công chúa dành cho nữ T415",
    "price": 9000,
    "original_price": 39000,
    "discount_pct": 77,
    "quantity": 35,
    "time_slot": "19:00",
    "image_url": "https://down-bs-vn.img.susercontent.com/vn-11134207-7r98o-luupl08wssnm60_tn",
    "product_link": "https://s.shopee.vn/an_redir?origin_link=https%3A%2F%2Fshopee.vn%2Fopaanlp%2F2123582%2F25228257996&affiliate_id=17351620126&sub_id=9k192606"
  },
  {
    "title": "BỘ QUẦN + ÁO MƯA SIÊU DAI TRONG SUỐT",
    "price": 9000,
    "original_price": 30000,
    "discount_pct": 70,
    "quantity": 28,
    "time_slot": "19:00",
    "image_url": "https://down-bs-vn.img.susercontent.com/vn-11134207-7ras8-md4jmhfohxkve1_tn",
    "product_link": "https://s.shopee.vn/an_redir?origin_link=https%3A%2F%2Fshopee.vn%2Fopaanlp%2F1101795773%2F26589595403&affiliate_id=17351620126&sub_id=9k192606"
  },
  {
    "title": "[🔥TẶNG 6 QUÀ] Bút Sáp Màu Deli 24 Màu Tươi Sáng, Màu Sáp Mịn, An Toàn Tiêu Chuẩn Châu Âu, Học Tập Mỹ Thuật",
    "price": 9000,
    "original_price": 34200,
    "discount_pct": 74,
    "quantity": 10,
    "time_slot": "19:00",
    "image_url": "https://down-bs-vn.img.susercontent.com/vn-11134207-81ztc-mpuzre60j1u3c6_tn",
    "product_link": "https://s.shopee.vn/an_redir?origin_link=https%3A%2F%2Fshopee.vn%2Fopaanlp%2F884990462%2F55911165565&affiliate_id=17351620126&sub_id=9k192606"
  },
  {
    "title": "Sách - Bộ Sách Bé Có Làm Được Không? -  Bộ sách cho trẻ từ 1 tuổi trở lên",
    "price": 9000,
    "original_price": 39000,
    "discount_pct": 77,
    "quantity": 40,
    "time_slot": "19:00",
    "image_url": "https://down-bs-vn.img.susercontent.com/vn-11134207-81ztc-mpswzxnhhxcd6a_tn",
    "product_link": "https://s.shopee.vn/an_redir?origin_link=https%3A%2F%2Fshopee.vn%2Fopaanlp%2F41925459%2F29452516056&affiliate_id=17351620126&sub_id=9k192606"
  },
  {
    "title": "Cuốn Sổ Ma Thuật 2in1 Vẽ Tranh Bằng Nước Kết Hợp Bóc Dán Kích Thích Tư Duy Thị Cho Bé",
    "price": 9000,
    "original_price": 35000,
    "discount_pct": 74,
    "quantity": 22,
    "time_slot": "19:00",
    "image_url": "https://down-bs-vn.img.susercontent.com/vn-11134207-81ztc-mn6kasro3bb6ee_tn",
    "product_link": "https://s.shopee.vn/an_redir?origin_link=https%3A%2F%2Fshopee.vn%2Fopaanlp%2F399573622%2F43112902503&affiliate_id=17351620126&sub_id=9k192606"
  },
  {
    "title": "Sách Ehon- Bộ Sách Chuyện Của Gấu Mèo (3 Cuốn) - Bộ sách dành cho bé trên 1+ - Finybooks",
    "price": 9000,
    "original_price": 45000,
    "discount_pct": 80,
    "quantity": 30,
    "time_slot": "19:00",
    "image_url": "https://down-bs-vn.img.susercontent.com/vn-11134207-81ztc-mps90n3d94i7d0_tn",
    "product_link": "https://s.shopee.vn/an_redir?origin_link=https%3A%2F%2Fshopee.vn%2Fopaanlp%2F1471846463%2F29229041529&affiliate_id=17351620126&sub_id=9k192606"
  },
  {
    "title": "[🔥4K/BÚT] Combo 5/10/20 Bút Bi Deli EQ32 Màu Pastel Ngòi 0.5mm Mực Xanh Nét Thanh Mảnh Cho Học Sinh Sinh Viên",
    "price": 9000,
    "original_price": 36000,
    "discount_pct": 75,
    "quantity": 30,
    "time_slot": "19:00",
    "image_url": "https://down-bs-vn.img.susercontent.com/vn-11134207-820l4-mjz0dzoz1p1ff5_tn",
    "product_link": "https://s.shopee.vn/an_redir?origin_link=https%3A%2F%2Fshopee.vn%2Fopaanlp%2F1021396369%2F57954993314&affiliate_id=17351620126&sub_id=9k192606"
  },
  {
    "title": "Sách - Rèn Luyện Kỹ Năng Sống Dành Cho Trẻ: Giỏi Giao Tiếp, Thói Quen Tốt, Tự Thoát Hiểm, Tự Bảo Vệ Mình (4 cuốn)",
    "price": 9000,
    "original_price": 60000,
    "discount_pct": 85,
    "quantity": 20,
    "time_slot": "19:00",
    "image_url": "https://down-bs-vn.img.susercontent.com/vn-11134207-7ras8-mc78v8txiwgla8_tn",
    "product_link": "https://s.shopee.vn/an_redir?origin_link=https%3A%2F%2Fshopee.vn%2Fopaanlp%2F1087367745%2F41558524106&affiliate_id=17351620126&sub_id=9k192606"
  },
  {
    "title": "Mũ Lưỡi Trai Thêu Chữ UNI Jussy Official Size To 62cm Nón Kết Nam Nữ Lòng Sâu Form Mềm Chất Cotton Thoáng Mát",
    "price": 9000,
    "original_price": 90000,
    "discount_pct": 90,
    "quantity": 25,
    "time_slot": "19:00",
    "image_url": "https://down-bs-vn.img.susercontent.com/vn-11134207-820l4-mg4sr244l6hb26_tn",
    "product_link": "https://s.shopee.vn/an_redir?origin_link=https%3A%2F%2Fshopee.vn%2Fopaanlp%2F22431875%2F24557557508&affiliate_id=17351620126&sub_id=9k192606"
  },
  {
    "title": "[Mã MII2430062 giảm 14% đơn 0Đ] [Top Value] Bột thông cống BLUE Đột phá gói 100g",
    "price": 16181,
    "original_price": 17399,
    "discount_pct": 7,
    "quantity": 10,
    "time_slot": "19:00",
    "image_url": "https://down-bs-vn.img.susercontent.com/vn-11134207-820l4-mfcf5ppe8xzdce_tn",
    "product_link": "https://s.shopee.vn/an_redir?origin_link=https%3A%2F%2Fshopee.vn%2Fopaanlp%2F1175586038%2F40172656060&affiliate_id=17351620126&sub_id=ot192606"
  },
  {
    "title": "12 Cuộn (4 bịch) Túi Đựng Rác Đen Kích Thước Lớn 65x55cm Tự Phân Hủy, Thân Thiện Với Môi Trường",
    "price": 22800,
    "original_price": 40000,
    "discount_pct": 43,
    "quantity": 60,
    "time_slot": "19:00",
    "image_url": "https://down-bs-vn.img.susercontent.com/vn-11134207-7ras8-mcdp4c1pfakl05_tn",
    "product_link": "https://s.shopee.vn/an_redir?origin_link=https%3A%2F%2Fshopee.vn%2Fopaanlp%2F1423867958%2F27588851347&affiliate_id=17351620126&sub_id=ot192606"
  },
  {
    "title": "Cọ má hồng chuyên nghiệp MAANGE Cọ trang điểm đa chức năng Cọ tạo khối 50g",
    "price": 26000,
    "original_price": 40000,
    "discount_pct": 35,
    "quantity": 105,
    "time_slot": "19:00",
    "image_url": "https://down-bs-vn.img.susercontent.com/cn-11134207-7r98o-lwz6bpaajo797a_tn",
    "product_link": "https://s.shopee.vn/an_redir?origin_link=https%3A%2F%2Fshopee.vn%2Fopaanlp%2F244551815%2F7631943470&affiliate_id=17351620126&sub_id=ot192606"
  },
  {
    "title": "Áo dán ngực silicon đẩy ngực đệm bàn tay siêu dính",
    "price": 29000,
    "original_price": 60000,
    "discount_pct": 52,
    "quantity": 10,
    "time_slot": "19:00",
    "image_url": "https://down-bs-vn.img.susercontent.com/vn-11134207-820l4-mfsjmqp2c2z0ea_tn",
    "product_link": "https://s.shopee.vn/an_redir?origin_link=https%3A%2F%2Fshopee.vn%2Fopaanlp%2F283418144%2F9152415620&affiliate_id=17351620126&sub_id=ot192606"
  },
  {
    "title": "[1kg] Phân bón tổng hợp NPK,phân bón Nitrophoska giúp cây tăng trưởng và phát triển toàn diện (PB-0)",
    "price": 29000,
    "original_price": 60000,
    "discount_pct": 52,
    "quantity": 50,
    "time_slot": "19:00",
    "image_url": "https://down-bs-vn.img.susercontent.com/vn-11134211-7ras8-m15edgv2szujd0_tn",
    "product_link": "https://s.shopee.vn/an_redir?origin_link=https%3A%2F%2Fshopee.vn%2Fopaanlp%2F1036761136%2F24736175543&affiliate_id=17351620126&sub_id=ot192606"
  },
  {
    "title": "Khăn Cao Cấp MK K19, Nhiều Size - Mềm Mịn, Thấm Hút Tốt - Cotton 100%, Đủ Màu Cho Bé Và Gia Đình",
    "price": 29000,
    "original_price": 60000,
    "discount_pct": 52,
    "quantity": 25,
    "time_slot": "19:00",
    "image_url": "https://down-bs-vn.img.susercontent.com/vn-11134207-820l4-mecz66b3ebcw59_tn",
    "product_link": "https://s.shopee.vn/an_redir?origin_link=https%3A%2F%2Fshopee.vn%2Fopaanlp%2F758905763%2F43417919939&affiliate_id=17351620126&sub_id=ot192606"
  },
  {
    "title": "Kính Áp tròng Softlens 4 Ống kính tiếp xúc Hydrogel 6 tháng Hàm lượng nước 38% Đường kính 14-14,5mm Thoải mái thoáng khí",
    "price": 29000,
    "original_price": 139000,
    "discount_pct": 79,
    "quantity": 20,
    "time_slot": "19:00",
    "image_url": "https://down-bs-vn.img.susercontent.com/cn-11134207-820l4-mlzr5h2xne2t50_tn",
    "product_link": "https://s.shopee.vn/an_redir?origin_link=https%3A%2F%2Fshopee.vn%2Fopaanlp%2F741458591%2F43828194347&affiliate_id=17351620126&sub_id=ot192606"
  },
  {
    "title": "Kính cường lực Iphone không viền đen Basefast full HD Chống Mẻ Cạnh cho ip 12 13 14 15 16 17 pro max",
    "price": 29000,
    "original_price": 80000,
    "discount_pct": 64,
    "quantity": 260,
    "time_slot": "19:00",
    "image_url": "https://down-bs-vn.img.susercontent.com/vn-11134207-820l4-mj6xefalqm86e6_tn",
    "product_link": "https://s.shopee.vn/an_redir?origin_link=https%3A%2F%2Fshopee.vn%2Fopaanlp%2F1051609213%2F23282529150&affiliate_id=17351620126&sub_id=ot192606"
  },
  {
    "title": "Đồ bấm lỗ tai (xỏ khuyên) cho người lớn, trẻ em, bé sơ sinh - xài 1 lần, an toàn, tiện lợi",
    "price": 29000,
    "original_price": 50000,
    "discount_pct": 42,
    "quantity": 15,
    "time_slot": "19:00",
    "image_url": "https://down-bs-vn.img.susercontent.com/0871201af053e00cf18e19b18429d3bd_tn",
    "product_link": "https://s.shopee.vn/an_redir?origin_link=https%3A%2F%2Fshopee.vn%2Fopaanlp%2F468448591%2F13736783373&affiliate_id=17351620126&sub_id=ot192606"
  },
  {
    "title": "Kính cường lực Iphone không che viền Chính hãng Basefast dán màn hình iP 11 12 13 14 15 16 17 promax",
    "price": 29000,
    "original_price": 75000,
    "discount_pct": 61,
    "quantity": 340,
    "time_slot": "19:00",
    "image_url": "https://down-bs-vn.img.susercontent.com/vn-11134207-81ztc-mos20beboirx59_tn",
    "product_link": "https://s.shopee.vn/an_redir?origin_link=https%3A%2F%2Fshopee.vn%2Fopaanlp%2F1632633681%2F41024506190&affiliate_id=17351620126&sub_id=ot192606"
  },
  {
    "title": "Áo Thun  Body Cổ Tròn Cộc Tay Chất Bozip Co Giãn 4 Chiều Cao Cấp MAIMIU_97 x THE BÚN Mã A01",
    "price": 29000,
    "original_price": 105000,
    "discount_pct": 72,
    "quantity": 20,
    "time_slot": "19:00",
    "image_url": "https://down-bs-vn.img.susercontent.com/vn-11134207-81ztc-mogyt6epm13574_tn",
    "product_link": "https://s.shopee.vn/an_redir?origin_link=https%3A%2F%2Fshopee.vn%2Fopaanlp%2F60321356%2F49308032490&affiliate_id=17351620126&sub_id=ot192606"
  },
  {
    "title": "Sách: Làm Bạn Cùng Con Trong Thời Đại Công Nghệ",
    "price": 29000,
    "original_price": 70000,
    "discount_pct": 59,
    "quantity": 15,
    "time_slot": "19:00",
    "image_url": "https://down-bs-vn.img.susercontent.com/vn-11134207-7r98o-lvwoa7um1fbv88_tn",
    "product_link": "https://s.shopee.vn/an_redir?origin_link=https%3A%2F%2Fshopee.vn%2Fopaanlp%2F495555744%2F24881464460&affiliate_id=17351620126&sub_id=ot192606"
  },
  {
    "title": "Khăn Trùm Đầu Ninja Fullface Kiêm Khẩu Trang Chống Nắng, Chống Bụi",
    "price": 29000,
    "original_price": 60000,
    "discount_pct": 52,
    "quantity": 24,
    "time_slot": "19:00",
    "image_url": "https://down-bs-vn.img.susercontent.com/vn-11134207-7ra0g-m95opeib4viaf2_tn",
    "product_link": "https://s.shopee.vn/an_redir?origin_link=https%3A%2F%2Fshopee.vn%2Fopaanlp%2F51246023%2F18675663433&affiliate_id=17351620126&sub_id=ot192606"
  },
  {
    "title": "Khẩu trang  Bambus  BU Baby ABB030000 Bổ sung",
    "price": 29000,
    "original_price": 65000,
    "discount_pct": 55,
    "quantity": 56,
    "time_slot": "19:00",
    "image_url": "https://down-bs-vn.img.susercontent.com/sg-11134275-82254-mhpx42huza4kf6_tn",
    "product_link": "https://s.shopee.vn/an_redir?origin_link=https%3A%2F%2Fshopee.vn%2Fopaanlp%2F353532270%2F47402407658&affiliate_id=17351620126&sub_id=ot192606"
  },
  {
    "title": "HM91010 Băng đô đính hạt Cài tóc sóng đính hạt, phụ kiện tóc nữ dễ thương HM68",
    "price": 29000,
    "original_price": 50000,
    "discount_pct": 42,
    "quantity": 45,
    "time_slot": "19:00",
    "image_url": "https://down-bs-vn.img.susercontent.com/vn-11134207-820l4-mi4qcjwkm58ga1_tn",
    "product_link": "https://s.shopee.vn/an_redir?origin_link=https%3A%2F%2Fshopee.vn%2Fopaanlp%2F832892001%2F54302953600&affiliate_id=17351620126&sub_id=ot192606"
  },
  {
    "title": "Mũ Chống Nắng Vành Rộng 12cm Kèm Khăn Che Full Vai Cổ JB48 Jussy Official Mũ Trùm Đầu Nữ Vải Cotton Chống Tia Uv",
    "price": 29000,
    "original_price": 50000,
    "discount_pct": 42,
    "quantity": 25,
    "time_slot": "19:00",
    "image_url": "https://down-bs-vn.img.susercontent.com/vn-11134207-7ras8-m5pwz5g7mvxyf5_tn",
    "product_link": "https://s.shopee.vn/an_redir?origin_link=https%3A%2F%2Fshopee.vn%2Fopaanlp%2F22431875%2F29874916641&affiliate_id=17351620126&sub_id=ot192606"
  },
  {
    "title": "Snack Bánh Gạo Nướng Haku Oishi Đủ Vị Dạng Túi Tiện Lợi",
    "price": 29000,
    "original_price": 36000,
    "discount_pct": 22,
    "quantity": 60,
    "time_slot": "19:00",
    "image_url": "https://down-bs-vn.img.susercontent.com/vn-11134207-820l4-mhk7ifd01qf93f_tn",
    "product_link": "https://s.shopee.vn/an_redir?origin_link=https%3A%2F%2Fshopee.vn%2Fopaanlp%2F651453702%2F29875435037&affiliate_id=17351620126&sub_id=ot192606"
  },
  {
    "title": "Kẹp tóc nữ Hàn Quốc Kẹp tóc nơ cao cấp màu đen",
    "price": 30800,
    "original_price": 40000,
    "discount_pct": 23,
    "quantity": 500,
    "time_slot": "19:00",
    "image_url": "https://down-bs-vn.img.susercontent.com/cn-11134207-820l4-mjjna4s49laa73_tn",
    "product_link": "https://s.shopee.vn/an_redir?origin_link=https%3A%2F%2Fshopee.vn%2Fopaanlp%2F408923068%2F29519692869&affiliate_id=17351620126&sub_id=ot192606"
  },
  {
    "title": "Kính râm phân cực cổ điển UV400 Câu cá đi xe đạp ngoài trời Unisex",
    "price": 31482,
    "original_price": 59400,
    "discount_pct": 47,
    "quantity": 10,
    "time_slot": "19:00",
    "image_url": "https://down-bs-vn.img.susercontent.com/sg-11134301-7rd5c-lwwi5lbu6d8qac_tn",
    "product_link": "https://s.shopee.vn/an_redir?origin_link=https%3A%2F%2Fshopee.vn%2Fopaanlp%2F1006220775%2F41659520190&affiliate_id=17351620126&sub_id=ot192606"
  },
  {
    "title": "Dụng cụ làm sạch cọ Xà phòng làm sạch cọ trang điểm, mini và di động, nhẹ nhàng trên lông cọ",
    "price": 60016,
    "original_price": 136400,
    "discount_pct": 56,
    "quantity": 200,
    "time_slot": "19:00",
    "image_url": "https://down-bs-vn.img.susercontent.com/cn-11134207-820l4-mjs6hpxwi70k01_tn",
    "product_link": "https://s.shopee.vn/an_redir?origin_link=https%3A%2F%2Fshopee.vn%2Fopaanlp%2F325226376%2F46704593687&affiliate_id=17351620126&sub_id=ot192606"
  },
  {
    "title": "Gạo St25+ Luá Vụ Mới Dẻo Vừa , Mềm Cơm , Thơm Nhẹ ( 5Ky )",
    "price": 123000,
    "original_price": 150000,
    "discount_pct": 18,
    "quantity": 100,
    "time_slot": "19:00",
    "image_url": "https://down-bs-vn.img.susercontent.com/vn-11134207-81ztc-mp4c1oni7cb08c_tn",
    "product_link": "https://s.shopee.vn/an_redir?origin_link=https%3A%2F%2Fshopee.vn%2Fopaanlp%2F35322524%2F3687964108&affiliate_id=17351620126&sub_id=ot192606"
  },
  {
    "title": "Gối kê cổ chữ U cao su non CECILA Gối Nệm Y Tế giúp giảm đau mỏi cổ cho dân văn phòng du lịch đi ô tô máy bay",
    "price": 124200,
    "original_price": 230000,
    "discount_pct": 46,
    "quantity": 220,
    "time_slot": "19:00",
    "image_url": "https://down-bs-vn.img.susercontent.com/vn-11134207-81ztc-mperlvkbflz686_tn",
    "product_link": "https://s.shopee.vn/an_redir?origin_link=https%3A%2F%2Fshopee.vn%2Fopaanlp%2F294644217%2F23451916792&affiliate_id=17351620126&sub_id=ot192606"
  }
]